odoo/addons/stock_quant_package_product_packaging/README.rst
odoo/addons/stock_quant_package_product_packaging/__init__.py
odoo/addons/stock_quant_package_product_packaging/__manifest__.py
odoo/addons/stock_quant_package_product_packaging/i18n/es.po
odoo/addons/stock_quant_package_product_packaging/i18n/it.po
odoo/addons/stock_quant_package_product_packaging/i18n/nl.po
odoo/addons/stock_quant_package_product_packaging/i18n/stock_quant_package_product_packaging.pot
odoo/addons/stock_quant_package_product_packaging/models/__init__.py
odoo/addons/stock_quant_package_product_packaging/models/product_product.py
odoo/addons/stock_quant_package_product_packaging/models/product_template.py
odoo/addons/stock_quant_package_product_packaging/models/stock_move_line.py
odoo/addons/stock_quant_package_product_packaging/models/stock_quant.py
odoo/addons/stock_quant_package_product_packaging/models/stock_quant_package.py
odoo/addons/stock_quant_package_product_packaging/readme/CONTRIBUTORS.md
odoo/addons/stock_quant_package_product_packaging/readme/DESCRIPTION.md
odoo/addons/stock_quant_package_product_packaging/static/description/icon.png
odoo/addons/stock_quant_package_product_packaging/static/description/index.html
odoo/addons/stock_quant_package_product_packaging/tests/__init__.py
odoo/addons/stock_quant_package_product_packaging/tests/common.py
odoo/addons/stock_quant_package_product_packaging/tests/test_auto_assign_package_type.py
odoo/addons/stock_quant_package_product_packaging/tests/test_stock_quant_package_product_packaging.py
odoo/addons/stock_quant_package_product_packaging/views/stock_quant_package.xml
odoo_addon_stock_quant_package_product_packaging-18.0.1.3.0.dist-info/METADATA
odoo_addon_stock_quant_package_product_packaging-18.0.1.3.0.dist-info/WHEEL
odoo_addon_stock_quant_package_product_packaging-18.0.1.3.0.dist-info/top_level.txt
odoo_addon_stock_quant_package_product_packaging-18.0.1.3.0.dist-info/RECORD
